middletools/__init__.py
middletools/book.py
middletools/exceptions.py
middletools/types.py
middletools-0.1.2.dist-info/LICENSE
middletools-0.1.2.dist-info/WHEEL
middletools-0.1.2.dist-info/METADATA
middletools-0.1.2.dist-info/RECORD
