Metadata-Version: 2.1
Name: middletools
Version: 0.1.2
Summary: This python library allows you integrate async-await middleware-based system to your project
Home-page: https://github.com/deknowny/middletools
License: MIT
Keywords: python,library,middlewares,create,utils
Author: deknowny
Author-email: deknowny@gmail.com
Requires-Python: >=3.7,<4.0
Classifier: Framework :: AsyncIO
Classifier: Intended Audience :: Developers
Classifier: License :: OSI Approved :: MIT License
Classifier: Programming Language :: Python :: 3
Classifier: Programming Language :: Python :: 3.7
Classifier: Programming Language :: Python :: 3.8
Classifier: Programming Language :: Python :: 3.9
Classifier: Topic :: Utilities
Classifier: Typing :: Typed
